dariah/__init__.py
dariah/api.py
dariah/core/__init__.py
dariah/core/modeling.py
dariah/core/utils.py
dariah/core/visualization.py
dariah/mallet/__init__.py
dariah/mallet/api.py
dariah/mallet/core.py
dariah/mallet/utils.py
dariah-2.0.2.dist-info/LICENSE
dariah-2.0.2.dist-info/WHEEL
dariah-2.0.2.dist-info/METADATA
dariah-2.0.2.dist-info/RECORD
