Metadata-Version: 2.1
Name: dariah
Version: 2.0.2
Summary: A library for topic modeling and visualization.
Home-page: https://dariah-de.github.io/Topics
License: Apache-2.0
Author: DARIAH-DE
Requires-Python: >=3.6,<4.0
Classifier: License :: OSI Approved :: Apache Software License
Classifier: Programming Language :: Python :: 3
Classifier: Programming Language :: Python :: 3.6
Classifier: Programming Language :: Python :: 3.7
Classifier: Programming Language :: Python :: 3.8
Requires-Dist: cophi (>=1.3.2,<2.0.0)
Requires-Dist: lda (>=2.0.0,<3.0.0)
Requires-Dist: matplotlib (>=3.2.1,<4.0.0)
Requires-Dist: numpy (>=1.19.2,<2.0.0)
Requires-Dist: pandas (>=1.1.2,<2.0.0)
Requires-Dist: regex (>=2020.1.8,<2021.0.0)
Requires-Dist: seaborn (>=0.11.0,<0.12.0)
Project-URL: Repository, https://github.com/DARIAH-DE/Topics
